<annotation>
	<folder></folder>
	<filename>00350_jpg.rf.f799829245e1feaca3a42a7aac6bade3.jpg</filename>
	<path>00350_jpg.rf.f799829245e1feaca3a42a7aac6bade3.jpg</path>
	<source>
		<database>roboflow.ai</database>
	</source>
	<size>
		<width>416</width>
		<height>416</height>
		<depth>3</depth>
	</size>
	<segmented>0</segmented>
	<object>
		<name>Dodge Ram Pickup 3500 Crew Cab 2010</name>
		<pose>Unspecified</pose>
		<truncated>0</truncated>
		<difficult>0</difficult>
		<occluded>0</occluded>
		<bndbox>
			<xmin>29</xmin>
			<xmax>398</xmax>
			<ymin>136</ymin>
			<ymax>306</ymax>
		</bndbox>
	</object>
</annotation>
