<annotation>
	<folder></folder>
	<filename>01115_jpg.rf.f823024cb8998e86a5a8dcf801ff6d7c.jpg</filename>
	<path>01115_jpg.rf.f823024cb8998e86a5a8dcf801ff6d7c.jpg</path>
	<source>
		<database>roboflow.ai</database>
	</source>
	<size>
		<width>416</width>
		<height>416</height>
		<depth>3</depth>
	</size>
	<segmented>0</segmented>
	<object>
		<name>BMW 3 Series Sedan 2012</name>
		<pose>Unspecified</pose>
		<truncated>0</truncated>
		<difficult>0</difficult>
		<occluded>0</occluded>
		<bndbox>
			<xmin>46</xmin>
			<xmax>372</xmax>
			<ymin>93</ymin>
			<ymax>330</ymax>
		</bndbox>
	</object>
</annotation>
