<annotation>
	<folder></folder>
	<filename>01326_jpg.rf.92ac5bc6189a64b676196b6833c4118e.jpg</filename>
	<path>01326_jpg.rf.92ac5bc6189a64b676196b6833c4118e.jpg</path>
	<source>
		<database>roboflow.ai</database>
	</source>
	<size>
		<width>416</width>
		<height>416</height>
		<depth>3</depth>
	</size>
	<segmented>0</segmented>
	<object>
		<name>Chevrolet Malibu Hybrid Sedan 2010</name>
		<pose>Unspecified</pose>
		<truncated>0</truncated>
		<difficult>0</difficult>
		<occluded>0</occluded>
		<bndbox>
			<xmin>22</xmin>
			<xmax>381</xmax>
			<ymin>119</ymin>
			<ymax>311</ymax>
		</bndbox>
	</object>
</annotation>
