<annotation>
	<folder></folder>
	<filename>03371_jpg.rf.a32698365f82b17bdaa50d4f12a9044b.jpg</filename>
	<path>03371_jpg.rf.a32698365f82b17bdaa50d4f12a9044b.jpg</path>
	<source>
		<database>roboflow.ai</database>
	</source>
	<size>
		<width>416</width>
		<height>416</height>
		<depth>3</depth>
	</size>
	<segmented>0</segmented>
	<object>
		<name>Chrysler Aspen SUV 2009</name>
		<pose>Unspecified</pose>
		<truncated>0</truncated>
		<difficult>0</difficult>
		<occluded>0</occluded>
		<bndbox>
			<xmin>5</xmin>
			<xmax>413</xmax>
			<ymin>139</ymin>
			<ymax>307</ymax>
		</bndbox>
	</object>
</annotation>
