<annotation>
	<folder></folder>
	<filename>03617_jpg.rf.9d867fc9508b718b4f2794227ab83dd1.jpg</filename>
	<path>03617_jpg.rf.9d867fc9508b718b4f2794227ab83dd1.jpg</path>
	<source>
		<database>roboflow.ai</database>
	</source>
	<size>
		<width>416</width>
		<height>416</height>
		<depth>3</depth>
	</size>
	<segmented>0</segmented>
	<object>
		<name>BMW X5 SUV 2007</name>
		<pose>Unspecified</pose>
		<truncated>0</truncated>
		<difficult>0</difficult>
		<occluded>0</occluded>
		<bndbox>
			<xmin>9</xmin>
			<xmax>400</xmax>
			<ymin>146</ymin>
			<ymax>328</ymax>
		</bndbox>
	</object>
</annotation>
