<annotation>
	<folder></folder>
	<filename>04165_jpg.rf.f4a9917d8e9795a00e607db277b03bfc.jpg</filename>
	<path>04165_jpg.rf.f4a9917d8e9795a00e607db277b03bfc.jpg</path>
	<source>
		<database>roboflow.ai</database>
	</source>
	<size>
		<width>416</width>
		<height>416</height>
		<depth>3</depth>
	</size>
	<segmented>0</segmented>
	<object>
		<name>Hyundai Veloster Hatchback 2012</name>
		<pose>Unspecified</pose>
		<truncated>0</truncated>
		<difficult>0</difficult>
		<occluded>0</occluded>
		<bndbox>
			<xmin>67</xmin>
			<xmax>340</xmax>
			<ymin>135</ymin>
			<ymax>287</ymax>
		</bndbox>
	</object>
</annotation>
