<annotation>
	<folder></folder>
	<filename>04422_jpg.rf.7846619f036ca75929d31a2ab2c8ca3b.jpg</filename>
	<path>04422_jpg.rf.7846619f036ca75929d31a2ab2c8ca3b.jpg</path>
	<source>
		<database>roboflow.ai</database>
	</source>
	<size>
		<width>416</width>
		<height>416</height>
		<depth>3</depth>
	</size>
	<segmented>0</segmented>
	<object>
		<name>Jeep Wrangler SUV 2012</name>
		<pose>Unspecified</pose>
		<truncated>0</truncated>
		<difficult>0</difficult>
		<occluded>0</occluded>
		<bndbox>
			<xmin>25</xmin>
			<xmax>393</xmax>
			<ymin>92</ymin>
			<ymax>332</ymax>
		</bndbox>
	</object>
</annotation>
