<annotation>
	<folder></folder>
	<filename>04669_jpg.rf.952cd532f05838e881e8439c4908d05a.jpg</filename>
	<path>04669_jpg.rf.952cd532f05838e881e8439c4908d05a.jpg</path>
	<source>
		<database>roboflow.ai</database>
	</source>
	<size>
		<width>416</width>
		<height>416</height>
		<depth>3</depth>
	</size>
	<segmented>0</segmented>
	<object>
		<name>AM General Hummer SUV 2000</name>
		<pose>Unspecified</pose>
		<truncated>0</truncated>
		<difficult>0</difficult>
		<occluded>0</occluded>
		<bndbox>
			<xmin>50</xmin>
			<xmax>372</xmax>
			<ymin>133</ymin>
			<ymax>358</ymax>
		</bndbox>
	</object>
</annotation>
