<annotation>
	<folder></folder>
	<filename>04796_jpg.rf.39217a3a2f14169faff988d0258860ea.jpg</filename>
	<path>04796_jpg.rf.39217a3a2f14169faff988d0258860ea.jpg</path>
	<source>
		<database>roboflow.ai</database>
	</source>
	<size>
		<width>416</width>
		<height>416</height>
		<depth>3</depth>
	</size>
	<segmented>0</segmented>
	<object>
		<name>Ford Mustang Convertible 2007</name>
		<pose>Unspecified</pose>
		<truncated>0</truncated>
		<difficult>0</difficult>
		<occluded>0</occluded>
		<bndbox>
			<xmin>19</xmin>
			<xmax>389</xmax>
			<ymin>101</ymin>
			<ymax>315</ymax>
		</bndbox>
	</object>
</annotation>
