<annotation>
	<folder></folder>
	<filename>05324_jpg.rf.7f5c621c91e4509b299c39e0bd9289e7.jpg</filename>
	<path>05324_jpg.rf.7f5c621c91e4509b299c39e0bd9289e7.jpg</path>
	<source>
		<database>roboflow.ai</database>
	</source>
	<size>
		<width>416</width>
		<height>416</height>
		<depth>3</depth>
	</size>
	<segmented>0</segmented>
	<object>
		<name>Acura TL Type-S 2008</name>
		<pose>Unspecified</pose>
		<truncated>0</truncated>
		<difficult>0</difficult>
		<occluded>0</occluded>
		<bndbox>
			<xmin>24</xmin>
			<xmax>395</xmax>
			<ymin>125</ymin>
			<ymax>296</ymax>
		</bndbox>
	</object>
</annotation>
