<annotation>
	<folder></folder>
	<filename>05861_jpg.rf.5a3e75828cac36d385159d61f2a0a11e.jpg</filename>
	<path>05861_jpg.rf.5a3e75828cac36d385159d61f2a0a11e.jpg</path>
	<source>
		<database>roboflow.ai</database>
	</source>
	<size>
		<width>416</width>
		<height>416</height>
		<depth>3</depth>
	</size>
	<segmented>0</segmented>
	<object>
		<name>BMW Z4 Convertible 2012</name>
		<pose>Unspecified</pose>
		<truncated>0</truncated>
		<difficult>0</difficult>
		<occluded>0</occluded>
		<bndbox>
			<xmin>83</xmin>
			<xmax>342</xmax>
			<ymin>135</ymin>
			<ymax>317</ymax>
		</bndbox>
	</object>
</annotation>
